{"dependencies":[{"name":"/Users/matt/development/Dollar-new/package.json","includedInParent":true,"mtime":1521936562892},{"name":"/Users/matt/development/Dollar-new/.babelrc","includedInParent":true,"mtime":1521932856924},{"name":"/Users/matt/development/Dollar-new/node_modules/@atlaskit/select/dist/package.json","includedInParent":true,"mtime":1521608541000},{"name":"./Select","loc":{"line":1,"column":24}},{"name":"./AsyncSelect","loc":{"line":2,"column":39}},{"name":"./CheckboxSelect","loc":{"line":3,"column":42}},{"name":"./CountrySelect","loc":{"line":4,"column":41}},{"name":"./RadioSelect","loc":{"line":5,"column":39}},{"name":"./CreatableSelect","loc":{"line":6,"column":43}},{"name":"./AsyncCreatableSelect","loc":{"line":7,"column":48}}],"generated":{"js":"'use strict';\n\nObject.defineProperty(exports, \"__esModule\", {\n  value: true\n});\n\nvar _Select = require('./Select');\n\nObject.defineProperty(exports, 'default', {\n  enumerable: true,\n  get: function () {\n    return _interopRequireDefault(_Select).default;\n  }\n});\n\nvar _AsyncSelect = require('./AsyncSelect');\n\nObject.defineProperty(exports, 'AsyncSelect', {\n  enumerable: true,\n  get: function () {\n    return _interopRequireDefault(_AsyncSelect).default;\n  }\n});\n\nvar _CheckboxSelect = require('./CheckboxSelect');\n\nObject.defineProperty(exports, 'CheckboxSelect', {\n  enumerable: true,\n  get: function () {\n    return _interopRequireDefault(_CheckboxSelect).default;\n  }\n});\n\nvar _CountrySelect = require('./CountrySelect');\n\nObject.defineProperty(exports, 'CountrySelect', {\n  enumerable: true,\n  get: function () {\n    return _interopRequireDefault(_CountrySelect).default;\n  }\n});\n\nvar _RadioSelect = require('./RadioSelect');\n\nObject.defineProperty(exports, 'RadioSelect', {\n  enumerable: true,\n  get: function () {\n    return _interopRequireDefault(_RadioSelect).default;\n  }\n});\n\nvar _CreatableSelect = require('./CreatableSelect');\n\nObject.defineProperty(exports, 'CreatableSelect', {\n  enumerable: true,\n  get: function () {\n    return _interopRequireDefault(_CreatableSelect).default;\n  }\n});\n\nvar _AsyncCreatableSelect = require('./AsyncCreatableSelect');\n\nObject.defineProperty(exports, 'AsyncCreatableSelect', {\n  enumerable: true,\n  get: function () {\n    return _interopRequireDefault(_AsyncCreatableSelect).default;\n  }\n});\n\nfunction _interopRequireDefault(obj) { return obj && obj.__esModule ? obj : { default: obj }; }","map":{"mappings":[{"name":"default","generated":{"line":12,"column":43},"source":"node_modules/@atlaskit/select/dist/esm/index.js","original":{"line":1,"column":9}},{"name":"default","generated":{"line":21,"column":48},"source":"node_modules/@atlaskit/select/dist/esm/index.js","original":{"line":2,"column":9}},{"name":"default","generated":{"line":30,"column":51},"source":"node_modules/@atlaskit/select/dist/esm/index.js","original":{"line":3,"column":9}},{"name":"default","generated":{"line":39,"column":50},"source":"node_modules/@atlaskit/select/dist/esm/index.js","original":{"line":4,"column":9}},{"name":"default","generated":{"line":48,"column":48},"source":"node_modules/@atlaskit/select/dist/esm/index.js","original":{"line":5,"column":9}},{"name":"default","generated":{"line":57,"column":52},"source":"node_modules/@atlaskit/select/dist/esm/index.js","original":{"line":6,"column":9}},{"name":"default","generated":{"line":66,"column":57},"source":"node_modules/@atlaskit/select/dist/esm/index.js","original":{"line":7,"column":9}}],"sources":{"node_modules/@atlaskit/select/dist/esm/index.js":"export { default } from './Select';\nexport { default as AsyncSelect } from './AsyncSelect';\nexport { default as CheckboxSelect } from './CheckboxSelect';\nexport { default as CountrySelect } from './CountrySelect';\nexport { default as RadioSelect } from './RadioSelect';\nexport { default as CreatableSelect } from './CreatableSelect';\nexport { default as AsyncCreatableSelect } from './AsyncCreatableSelect';"},"lineCount":null}},"hash":"446ef8231c3465d995ca0690cd6b8dd5","cacheData":{"env":{}}}