{"dependencies":[{"name":"./type","loc":{"line":1,"column":22}}],"generated":{"js":"\"use strict\";\n\nObject.defineProperty(exports, \"__esModule\", {\n  value: true\n});\nexports.getBlob = getBlob;\nexports.sliceBlob = sliceBlob;\n\nvar _type = require(\"./type\");\n\nvar type = _interopRequireWildcard(_type);\n\nfunction _interopRequireWildcard(obj) { if (obj && obj.__esModule) { return obj; } else { var newObj = {}; if (obj != null) { for (var key in obj) { if (Object.prototype.hasOwnProperty.call(obj, key)) newObj[key] = obj[key]; } } newObj.default = obj; return newObj; } }\n\nfunction getBlobBuilder() {\n  if (typeof BlobBuilder !== 'undefined') {\n    return BlobBuilder;\n  } else if (typeof WebKitBlobBuilder !== 'undefined') {\n    return WebKitBlobBuilder;\n  } else {\n    return undefined;\n  }\n}\n/**\n * Concatenates one or more values together and converts them to a Blob.\n *\n * @param var_args The values that will make up the resulting blob.\n * @return The blob.\n */\nfunction getBlob() {\n  var var_args = [];\n  for (var _i = 0; _i < arguments.length; _i++) {\n    var_args[_i] = arguments[_i];\n  }\n  var BlobBuilder = getBlobBuilder();\n  if (BlobBuilder !== undefined) {\n    var bb = new BlobBuilder();\n    for (var i = 0; i < var_args.length; i++) {\n      bb.append(var_args[i]);\n    }\n    return bb.getBlob();\n  } else {\n    if (type.isNativeBlobDefined()) {\n      return new Blob(var_args);\n    } else {\n      throw Error(\"This browser doesn't seem to support creating Blobs\");\n    }\n  }\n}\n/**\n * Slices the blob. The returned blob contains data from the start byte\n * (inclusive) till the end byte (exclusive). Negative indices cannot be used.\n *\n * @param blob The blob to be sliced.\n * @param start Index of the starting byte.\n * @param end Index of the ending byte.\n * @return The blob slice or null if not supported.\n */\nfunction sliceBlob(blob, start, end) {\n  if (blob.webkitSlice) {\n    return blob.webkitSlice(start, end);\n  } else if (blob.mozSlice) {\n    return blob.mozSlice(start, end);\n  } else if (blob.slice) {\n    return blob.slice(start, end);\n  }\n  return null;\n}\n\n//# sourceMappingURL=fs.js.map"},"hash":"4b5b7f410d345a8f62026e004e5ee739"}