{"dependencies":[{"name":"/Users/matt/development/Dollar-new/package.json","includedInParent":true,"mtime":1521939492050},{"name":"/Users/matt/development/Dollar-new/.babelrc","includedInParent":true,"mtime":1521932856924},{"name":"/Users/matt/development/Dollar-new/node_modules/@atlaskit/droplist/dist/package.json","includedInParent":true,"mtime":1520484024000},{"name":"./components/Droplist","loc":{"line":1,"column":24}},{"name":"./components/Item","loc":{"line":2,"column":32}},{"name":"./components/Group","loc":{"line":3,"column":33}},{"name":"./styled/Item","loc":{"line":4,"column":30}}],"generated":{"js":"'use strict';\n\nObject.defineProperty(exports, \"__esModule\", {\n  value: true\n});\n\nvar _Droplist = require('./components/Droplist');\n\nObject.defineProperty(exports, 'default', {\n  enumerable: true,\n  get: function () {\n    return _interopRequireDefault(_Droplist).default;\n  }\n});\n\nvar _Item = require('./components/Item');\n\nObject.defineProperty(exports, 'Item', {\n  enumerable: true,\n  get: function () {\n    return _interopRequireDefault(_Item).default;\n  }\n});\n\nvar _Group = require('./components/Group');\n\nObject.defineProperty(exports, 'Group', {\n  enumerable: true,\n  get: function () {\n    return _interopRequireDefault(_Group).default;\n  }\n});\n\nvar _Item2 = require('./styled/Item');\n\nObject.defineProperty(exports, 'SecondaryText', {\n  enumerable: true,\n  get: function () {\n    return _Item2.SecondaryText;\n  }\n});\n\nfunction _interopRequireDefault(obj) { return obj && obj.__esModule ? obj : { default: obj }; }","map":{"mappings":[{"name":"default","generated":{"line":12,"column":45},"source":"node_modules/@atlaskit/droplist/dist/esm/index.js","original":{"line":1,"column":9}},{"name":"default","generated":{"line":21,"column":41},"source":"node_modules/@atlaskit/droplist/dist/esm/index.js","original":{"line":2,"column":9}},{"name":"default","generated":{"line":30,"column":42},"source":"node_modules/@atlaskit/droplist/dist/esm/index.js","original":{"line":3,"column":9}},{"name":"SecondaryText","generated":{"line":39,"column":18},"source":"node_modules/@atlaskit/droplist/dist/esm/index.js","original":{"line":4,"column":9}}],"sources":{"node_modules/@atlaskit/droplist/dist/esm/index.js":"export { default } from './components/Droplist';\nexport { default as Item } from './components/Item';\nexport { default as Group } from './components/Group';\nexport { SecondaryText } from './styled/Item';"},"lineCount":null}},"hash":"730caa17106a91b6a5d37d624405954a","cacheData":{"env":{}}}